elmclient/__init__.py
elmclient/__meta__.py
elmclient/_app.py
elmclient/_ccm.py
elmclient/_config.py
elmclient/_customScenarios.py
elmclient/_gcm.py
elmclient/_newtypesystem.py
elmclient/_project.py
elmclient/_qm.py
elmclient/_qmrestapi.py
elmclient/_queryparser.py
elmclient/_relm.py
elmclient/_rm.py
elmclient/_typesystem.py
elmclient/_validate.py
elmclient/httpops.py
elmclient/oslcqueryapi.py
elmclient/rdfxml.py
elmclient/resource.py
elmclient/server.py
elmclient/testcase.py
elmclient/utils.py
elmclient/examples/DN_SIMPLE_MODULESTRUCTURE.md
elmclient/examples/OSLCQUERY.md
elmclient/examples/REPREST.md
elmclient/examples/REQIF_IO.md
elmclient/examples/batchquery.py
elmclient/examples/ccm_simple_attachmentdownload.py
elmclient/examples/ccm_simple_findworkitem.py
elmclient/examples/dn_basic_discovery.py
elmclient/examples/dn_basic_oslcquery.py
elmclient/examples/dn_resource_scenario1.py
elmclient/examples/dn_resource_scenario2.py
elmclient/examples/dn_resource_scenario3.py
elmclient/examples/dn_resource_test.py
elmclient/examples/dn_simple_createartifact.py
elmclient/examples/dn_simple_createfolderandartifact.py
elmclient/examples/dn_simple_createfolderpath.py
elmclient/examples/dn_simple_createmodule.py
elmclient/examples/dn_simple_deleteartifact.py
elmclient/examples/dn_simple_modifylink.py
elmclient/examples/dn_simple_modulestructure.py
elmclient/examples/dn_simple_oslcquery.py
elmclient/examples/dn_simple_represt.py
elmclient/examples/dn_simple_typesystemimport.py
elmclient/examples/dn_simple_typesystemimport_cs.py
elmclient/examples/dn_simple_updateartifact.py
elmclient/examples/dncompare.py
elmclient/examples/etm_scenario1.py
elmclient/examples/etm_scenario2.py
elmclient/examples/etm_scenario3.py
elmclient/examples/etm_simple_updatetestresult.py
elmclient/examples/log2seq.py
elmclient/examples/oneperminute.py
elmclient/examples/oslcquery.py
elmclient/examples/represt.py
elmclient/examples/reqif_io.py
elmclient/examples/trsreader.py
elmclient-0.36.0.dist-info/licenses/LICENSE
elmclient-0.36.0.dist-info/METADATA
elmclient-0.36.0.dist-info/WHEEL
elmclient-0.36.0.dist-info/entry_points.txt
elmclient-0.36.0.dist-info/top_level.txt
elmclient-0.36.0.dist-info/RECORD
