Metadata-Version: 2.4
Name: elmclient
Version: 0.36.0
Summary: Python client for ELM with examples of OSLC Query, ReqIF import/export, Reportable REST, and more
Home-page: https://github.com/IBM/ELM-Python-Client
Author: Ian Barnard
License: MIT
Classifier: License :: OSI Approved :: MIT License
Classifier: Programming Language :: Python :: 3
Classifier: Programming Language :: Python :: 3.9
Classifier: Programming Language :: Python :: 3.10
Classifier: Programming Language :: Python :: 3.11
Classifier: Programming Language :: Python :: 3.12
License-File: LICENSE
Requires-Dist: CacheControl
Requires-Dist: anytree
Requires-Dist: colorama
Requires-Dist: cryptography
Requires-Dist: lark_parser
Requires-Dist: lockfile
Requires-Dist: lxml
Requires-Dist: openpyxl
Requires-Dist: python-dateutil
Requires-Dist: pytz
Requires-Dist: requests
Requires-Dist: requests_toolbelt
Requires-Dist: tqdm
Requires-Dist: urllib3
Requires-Dist: bump2version
Requires-Dist: twine
Requires-Dist: filelock
Dynamic: author
Dynamic: classifier
Dynamic: description
Dynamic: description-content-type
Dynamic: home-page
Dynamic: license
Dynamic: license-file
Dynamic: requires-dist
Dynamic: summary
